{"schema":"s2s_action_record_v1","action":"descend_stairs","domain":"LOCOMOTION","domain_description":"Whole-body movement \u2014 walking, running, climbing","robot_use":"Bipedal robots, exoskeletons, prosthetic legs, quadrupeds","person_id":"uci_s05","dataset_source":"UCI_HAR","duration_s":2.54,"n_samples":128,"imu_tier":"GOLD","physics_tier":"BRONZE","physics_score":51,"physics_laws_passed":["rigid_body_kinematics","jerk_bounds","imu_internal_consistency"],"physics_laws_failed":["resonance_frequency"],"jerk_p95_ms3":194.8,"imu_coupling_r":-0.11,"_signing_key_id":"efeb7fb178378cb2","_signing_mode":"Ed25519","_signed_at_ns":1772242404311914000,"_signature":"RujLVq1M9q1xsnZk7ndEhDAHk6BKkBBnpbJ-qV34ymx_jvktb2b7735JTx0L43gh1QmB5Pxdo9OIscic6v4iBg=="}