{"schema":"s2s_action_record_v1","action":"stand_up","domain":"LOCOMOTION","domain_description":"Whole-body movement \u2014 walking, running, climbing","robot_use":"Bipedal robots, exoskeletons, prosthetic legs, quadrupeds","person_id":"uci_s26","dataset_source":"UCI_HAR","duration_s":2.54,"n_samples":128,"imu_tier":"GOLD","physics_tier":"SILVER","physics_score":62,"physics_laws_passed":["resonance_frequency","jerk_bounds","imu_internal_consistency"],"physics_laws_failed":["rigid_body_kinematics"],"jerk_p95_ms3":4.2,"imu_coupling_r":-0.5814,"_signing_key_id":"efeb7fb178378cb2","_signing_mode":"Ed25519","_signed_at_ns":1772242663737632000,"_signature":"hR-ZJNvh3EaRIScqY05eBgp3QcA0ps_yP3TYkmSH8nphlo_2RzM2vBGJ89fLL20ExFe2CC0A6ibm961FKoY3CA=="}